{"series": {"feedUrl": "http://feeds2.feedburner.com/fsn", "genres": ["Business News", "Podcasts", "Business", "Investing", "News & Politics", "Education", "Educational Technology"], "title": "Financial Sense(R) Newshour", "country": "USA", "author": "Jim Puplava", "imageUrlLg": "http://is3.mzstatic.com/image/thumb/Music62/v4/53/a5/2c/53a52cea-22d6-3ec6-8ccb-903020b6fde6/source/600x600bb.jpg", "imageUrlSm": "http://is3.mzstatic.com/image/thumb/Music62/v4/53/a5/2c/53a52cea-22d6-3ec6-8ccb-903020b6fde6/source/60x60bb.jpg", "type": "series", "id": 306759846}, "episodes": [{"seriesId": 306759846, "seriesTitle": "Financial Sense(R) Newshour", "pubDate": 1488787200, "title": "The Most Important Retirement Decision You Will Make  2017-03-06", "author": "Jim Puplava", "summary": "Applying Common Sense to the Markets", "duration": "40:48", "imageUrlLg": "http://is3.mzstatic.com/image/thumb/Music62/v4/53/a5/2c/53a52cea-22d6-3ec6-8ccb-903020b6fde6/source/600x600bb.jpg", "imageUrlSm": "http://is3.mzstatic.com/image/thumb/Music62/v4/53/a5/2c/53a52cea-22d6-3ec6-8ccb-903020b6fde6/source/60x60bb.jpg", "audioUrl": "http://feedproxy.google.com/~r/fsn/~5/W3GyqY3eZgc/fsn2017-0306-1.mp3", "type": "episode", "tags": ["jim puplava", "jim", "puplava", "financial", "financial sense", "financial sense newshour", "gold", "silver", "investing", "silver investing"]}, {"seriesId": 306759846, "seriesTitle": "Financial Sense(R) Newshour", "pubDate": 1488614400, "title": "Hour 2  7 Megatrends for the Next Decade  Investment Implications  2017-03-04", "author": "Jim Puplava", "summary": "Applying Common Sense to the Markets", "duration": "61:48", "imageUrlLg": "http://is3.mzstatic.com/image/thumb/Music62/v4/53/a5/2c/53a52cea-22d6-3ec6-8ccb-903020b6fde6/source/600x600bb.jpg", "imageUrlSm": "http://is3.mzstatic.com/image/thumb/Music62/v4/53/a5/2c/53a52cea-22d6-3ec6-8ccb-903020b6fde6/source/60x60bb.jpg", "audioUrl": "http://feedproxy.google.com/~r/fsn/~5/mWy_K6jjI0I/fsn2017-0304-2.mp3", "type": "episode", "tags": ["jim puplava", "jim", "puplava", "financial", "financial sense", "financial sense newshour", "gold", "silver", "investing", "silver investing"]}, {"seriesId": 306759846, "seriesTitle": "Financial Sense(R) Newshour", "pubDate": 1488614400, "title": "Hour 1  Ralph Acampora: Trump Honeymoon Close to Ending  2017-03-04", "author": "Jim Puplava", "summary": "Applying Common Sense to the Markets", "duration": "50:38", "imageUrlLg": "http://is3.mzstatic.com/image/thumb/Music62/v4/53/a5/2c/53a52cea-22d6-3ec6-8ccb-903020b6fde6/source/600x600bb.jpg", "imageUrlSm": "http://is3.mzstatic.com/image/thumb/Music62/v4/53/a5/2c/53a52cea-22d6-3ec6-8ccb-903020b6fde6/source/60x60bb.jpg", "audioUrl": "http://feedproxy.google.com/~r/fsn/~5/X61rfJ_secg/fsn2017-0304-1.mp3", "type": "episode", "tags": ["jim puplava", "jim", "puplava", "financial", "financial sense", "financial sense newshour", "gold", "silver", "investing", "silver investing"]}, {"seriesId": 306759846, "seriesTitle": "Financial Sense(R) Newshour", "pubDate": 1488528000, "title": "Rosenberg: This Is Not Normal  Preview. 2017-03-03", "author": "Jim Puplava", "summary": "Applying Common Sense to the Markets", "duration": "4:21", "imageUrlLg": "http://is3.mzstatic.com/image/thumb/Music62/v4/53/a5/2c/53a52cea-22d6-3ec6-8ccb-903020b6fde6/source/600x600bb.jpg", "imageUrlSm": "http://is3.mzstatic.com/image/thumb/Music62/v4/53/a5/2c/53a52cea-22d6-3ec6-8ccb-903020b6fde6/source/60x60bb.jpg", "audioUrl": "http://feedproxy.google.com/~r/fsn/~5/ZzZnAo9ykrQ/fsn2017-0303-1.mp3", "type": "episode", "tags": ["jim puplava", "jim", "puplava", "financial", "financial sense", "financial sense newshour", "gold", "silver", "investing", "silver investing"]}, {"seriesId": 306759846, "seriesTitle": "Financial Sense(R) Newshour", "pubDate": 1488441600, "title": "Massive Numbers of People Are Renouncing US Citizenship  Preview. 2017-03-02", "author": "Jim Puplava", "summary": "Applying Common Sense to the Markets", "duration": "4:56", "imageUrlLg": "http://is3.mzstatic.com/image/thumb/Music62/v4/53/a5/2c/53a52cea-22d6-3ec6-8ccb-903020b6fde6/source/600x600bb.jpg", "imageUrlSm": "http://is3.mzstatic.com/image/thumb/Music62/v4/53/a5/2c/53a52cea-22d6-3ec6-8ccb-903020b6fde6/source/60x60bb.jpg", "audioUrl": "http://feedproxy.google.com/~r/fsn/~5/LqAtcSLkLgg/fsn2017-0302-1.mp3", "type": "episode", "tags": ["jim puplava", "jim", "puplava", "financial", "financial sense", "financial sense newshour", "gold", "silver", "investing", "silver investing"]}, {"seriesId": 306759846, "seriesTitle": "Financial Sense(R) Newshour", "pubDate": 1488355200, "title": "Jeffrey Saut on Fiscal Policy Outlook, Market Valuations  Preview. 2017-03-01", "author": "Jim Puplava", "summary": "Applying Common Sense to the Markets", "duration": "4:34", "imageUrlLg": "http://is3.mzstatic.com/image/thumb/Music62/v4/53/a5/2c/53a52cea-22d6-3ec6-8ccb-903020b6fde6/source/600x600bb.jpg", "imageUrlSm": "http://is3.mzstatic.com/image/thumb/Music62/v4/53/a5/2c/53a52cea-22d6-3ec6-8ccb-903020b6fde6/source/60x60bb.jpg", "audioUrl": "http://feedproxy.google.com/~r/fsn/~5/PUT_OY_aOFM/fsn2017-0301-1.mp3", "type": "episode", "tags": ["jim puplava", "jim", "puplava", "financial", "financial sense", "financial sense newshour", "gold", "silver", "investing", "silver investing"]}, {"seriesId": 306759846, "seriesTitle": "Financial Sense(R) Newshour", "pubDate": 1488268800, "title": "Long-term Care  What You Need to Know and How to Prepare for It  2017-02-28", "author": "Jim Puplava", "summary": "Applying Common Sense to the Markets", "duration": "34:50", "imageUrlLg": "http://is3.mzstatic.com/image/thumb/Music62/v4/53/a5/2c/53a52cea-22d6-3ec6-8ccb-903020b6fde6/source/600x600bb.jpg", "imageUrlSm": "http://is3.mzstatic.com/image/thumb/Music62/v4/53/a5/2c/53a52cea-22d6-3ec6-8ccb-903020b6fde6/source/60x60bb.jpg", "audioUrl": "http://feedproxy.google.com/~r/fsn/~5/to4mIf7stbA/fsn2017-0228-1.mp3", "type": "episode", "tags": ["jim puplava", "jim", "puplava", "financial", "financial sense", "financial sense newshour", "gold", "silver", "investing", "silver investing"]}, {"seriesId": 306759846, "seriesTitle": "Financial Sense(R) Newshour", "pubDate": 1488182400, "title": "Inflation  The Silent and Deadly Killer  2017-02-27", "author": "Jim Puplava", "summary": "Applying Common Sense to the Markets", "duration": "35:27", "imageUrlLg": "http://is3.mzstatic.com/image/thumb/Music62/v4/53/a5/2c/53a52cea-22d6-3ec6-8ccb-903020b6fde6/source/600x600bb.jpg", "imageUrlSm": "http://is3.mzstatic.com/image/thumb/Music62/v4/53/a5/2c/53a52cea-22d6-3ec6-8ccb-903020b6fde6/source/60x60bb.jpg", "audioUrl": "http://feedproxy.google.com/~r/fsn/~5/iPkXnOEjm9s/fsn2017-0227-1.mp3", "type": "episode", "tags": ["jim puplava", "jim", "puplava", "financial", "financial sense", "financial sense newshour", "gold", "silver", "investing", "silver investing"]}, {"seriesId": 306759846, "seriesTitle": "Financial Sense(R) Newshour", "pubDate": 1488009600, "title": "Hour 2  7 Megatrends and the Next Crash  2017-02-25", "author": "Jim Puplava", "summary": "Applying Common Sense to the Markets", "duration": "75:28", "imageUrlLg": "http://is3.mzstatic.com/image/thumb/Music62/v4/53/a5/2c/53a52cea-22d6-3ec6-8ccb-903020b6fde6/source/600x600bb.jpg", "imageUrlSm": "http://is3.mzstatic.com/image/thumb/Music62/v4/53/a5/2c/53a52cea-22d6-3ec6-8ccb-903020b6fde6/source/60x60bb.jpg", "audioUrl": "http://feedproxy.google.com/~r/fsn/~5/ElTmCjjxBlE/fsn2017-0225-2.mp3", "type": "episode", "tags": ["jim puplava", "jim", "puplava", "financial", "financial sense", "financial sense newshour", "gold", "silver", "investing", "silver investing"]}, {"seriesId": 306759846, "seriesTitle": "Financial Sense(R) Newshour", "pubDate": 1488009600, "title": "Hour 1  John Kosar on Technicals; Matias Cortes on Automation  2017-02-25", "author": "Jim Puplava", "summary": "Applying Common Sense to the Markets", "duration": "55:58", "imageUrlLg": "http://is3.mzstatic.com/image/thumb/Music62/v4/53/a5/2c/53a52cea-22d6-3ec6-8ccb-903020b6fde6/source/600x600bb.jpg", "imageUrlSm": "http://is3.mzstatic.com/image/thumb/Music62/v4/53/a5/2c/53a52cea-22d6-3ec6-8ccb-903020b6fde6/source/60x60bb.jpg", "audioUrl": "http://feedproxy.google.com/~r/fsn/~5/NUI8CQABwyE/fsn2017-0225-1.mp3", "type": "episode", "tags": ["jim puplava", "jim", "puplava", "financial", "financial sense", "financial sense newshour", "gold", "silver", "investing", "silver investing"]}]}